light_food/light_food.vhd
LIBRARY ieee;
USE ieee.std_logic_1164.ALL;

ENTITY light_food IS
    PORT (
        clk : IN STD_LOGIC;
        A : IN STD_LOGIC;
        B : IN STD_LOGIC;
        C : IN STD_LOGIC;
        D : IN STD_LOGIC;
        L : OUT STD_LOGIC
    );
END ENTITY light_food;

ARCHITECTURE behavior OF light_food IS
BEGIN
    PROCESS (clk)
    BEGIN
        IF rising_edge(clk) THEN
            L <= (A AND B) OR (A AND C) OR (B AND C AND D);
        END IF;
    END PROCESS;
END ARCHITECTURE behavior;

light_food/tb_light_food.vhd
LIBRARY ieee;
USE ieee.std_logic_1164.ALL;

ENTITY tb_light_food IS
END ENTITY tb_light_food;

ARCHITECTURE sim OF tb_light_food IS

    COMPONENT light_food
        PORT (
            clk : IN STD_LOGIC;
            A : IN STD_LOGIC;
            B : IN STD_LOGIC;
            C : IN STD_LOGIC;
            D : IN STD_LOGIC;
            L : OUT STD_LOGIC
        );
    END COMPONENT;

    SIGNAL clk : STD_LOGIC := '0';
    SIGNAL A, B, C, D : STD_LOGIC := '0';
    SIGNAL L : STD_LOGIC;

BEGIN

    UUT : light_food
    PORT MAP(
        clk => clk,
        A => A,
        B => B,
        C => C,
        D => D,
        L => L
    );

    clk_process : PROCESS
    BEGIN
        WHILE now < 160 ns LOOP
            clk <= NOT clk;
            WAIT FOR 5 ns;
        END LOOP;
        WAIT;
    END PROCESS;

    stim_process : PROCESS
    BEGIN
        A <= '0';
        B <= '0';
        C <= '0';
        D <= '0';
        WAIT FOR 10 ns;
        A <= '0';
        B <= '0';
        C <= '0';
        D <= '1';
        WAIT FOR 10 ns;
        A <= '0';
        B <= '0';
        C <= '1';
        D <= '0';
        WAIT FOR 10 ns;
        A <= '0';
        B <= '0';
        C <= '1';
        D <= '1';
        WAIT FOR 10 ns;
        A <= '0';
        B <= '1';
        C <= '0';
        D <= '0';
        WAIT FOR 10 ns;
        A <= '0';
        B <= '1';
        C <= '0';
        D <= '1';
        WAIT FOR 10 ns;
        A <= '0';
        B <= '1';
        C <= '1';
        D <= '0';
        WAIT FOR 10 ns;
        A <= '0';
        B <= '1';
        C <= '1';
        D <= '1';
        WAIT FOR 10 ns;
        A <= '1';
        B <= '0';
        C <= '0';
        D <= '0';
        WAIT FOR 10 ns;
        A <= '1';
        B <= '0';
        C <= '0';
        D <= '1';
        WAIT FOR 10 ns;
        A <= '1';
        B <= '0';
        C <= '1';
        D <= '0';
        WAIT FOR 10 ns;
        A <= '1';
        B <= '0';
        C <= '1';
        D <= '1';
        WAIT FOR 10 ns;
        A <= '1';
        B <= '1';
        C <= '0';
        D <= '0';
        WAIT FOR 10 ns;
        A <= '1';
        B <= '1';
        C <= '0';
        D <= '1';
        WAIT FOR 10 ns;
        A <= '1';
        B <= '1';
        C <= '1';
        D <= '0';
        WAIT FOR 10 ns;
        A <= '1';
        B <= '1';
        C <= '1';
        D <= '1';
        WAIT FOR 10 ns;
        WAIT;
    END PROCESS;

END ARCHITECTURE sim;

light_food/light_food.vcd
$date
  Fri Sep 19 15:50:30 2025
$end
$version
  GHDL v0
$end
$timescale
  1 fs
$end
$scope module standard $end
$upscope $end
$scope module std_logic_1164 $end
$upscope $end
$scope module tb_light_food $end
$var reg 1 ! clk $end
$var reg 1 " a $end
$var reg 1 # b $end
$var reg 1 $ c $end
$var reg 1 % d $end
$var reg 1 & l $end
$scope module uut $end
$var reg 1 ' clk $end
$var reg 1 ( a $end
$var reg 1 ) b $end
$var reg 1 * c $end
$var reg 1 + d $end
$var reg 1 , l $end
$upscope $end
$upscope $end
$enddefinitions $end
#0
1!
0"
0#
0$
0%
0&
1'
0(
0)
0*
0+
0,
#5000000
0!
0'
#10000000
1!
1%
1'
1+
#15000000
0!
0'
#20000000
1!
1$
0%
1'
1*
0+
#25000000
0!
0'
#30000000
1!
1%
1'
1+
#35000000
0!
0'
#40000000
1!
1#
0$
0%
1'
1)
0*
0+
#45000000
0!
0'
#50000000
1!
1%
1'
1+
#55000000
0!
0'
#60000000
1!
1$
0%
1'
1*
0+
#65000000
0!
0'
#70000000
1!
1%
1&
1'
1+
1,
#75000000
0!
0'
#80000000
1!
1"
0#
0$
0%
0&
1'
1(
0)
0*
0+
0,
#85000000
0!
0'
#90000000
1!
1%
1'
1+
#95000000
0!
0'
#100000000
1!
1$
0%
1&
1'
1*
0+
1,
#105000000
0!
0'
#110000000
1!
1%
1'
1+
#115000000
0!
0'
#120000000
1!
1#
0$
0%
1'
1)
0*
0+
#125000000
0!
0'
#130000000
1!
1%
1'
1+
#135000000
0!
0'
#140000000
1!
1$
0%
1'
1*
0+
#145000000
0!
0'
#150000000
1!
1%
1'
1+
