substrator_completo/subtratorcompleto.v
module subtratorcompleto(A, B, Cin, S, Cout);
input A, B, Cin;
output S, Cout;

assign S = A ^ B ^ Cin;
assign Cout = (~A & B) | (~A & Cin) | (B & Cin);
endmodule

substrator_completo/subtratorcompleto_tb.v
`include "subtratorcompleto.v"
`timescale 1ns/100ps 

module subtratorcompleto_tb;
reg A0, B0, Cin0;
wire S0, Cout0;

subtratorcompleto utt(.A(A0), .B(B0), .Cin(Cin0), .S(S0), .Cout(Cout0));

initial begin
    $dumpfile("subtratorcompleto.vcd");
    $dumpvars(0, subtratorcompleto_tb);
         A0 = 0; B0 = 0; Cin0 = 0;
    #10; A0 = 0; B0 = 0; Cin0 = 1;
    #10; A0 = 0; B0 = 1; Cin0 = 0;
    #10; A0 = 0; B0 = 1; Cin0 = 1;
    #10; A0 = 1; B0 = 0; Cin0 = 0;
    #10; A0 = 1; B0 = 0; Cin0 = 1;
    #10; A0 = 1; B0 = 1; Cin0 = 0;
    #10; A0 = 1; B0 = 1; Cin0 = 1;
    #10; $finish;
end

endmodule

substrator_completo/subtratorcompleto.vcd
$date
	Tue Aug 19 20:03:17 2025
$end
$version
	Icarus Verilog
$end
$timescale
	100ps
$end
$scope module subtratorcompleto_tb $end
$var wire 1 ! S0 $end
$var wire 1 " Cout0 $end
$var reg 1 # A0 $end
$var reg 1 $ B0 $end
$var reg 1 % Cin0 $end
$scope module utt $end
$var wire 1 # A $end
$var wire 1 $ B $end
$var wire 1 % Cin $end
$var wire 1 " Cout $end
$var wire 1 ! S $end
$upscope $end
$upscope $end
$enddefinitions $end
$comment Show the parameter values. $end
$dumpall
$end
#0
$dumpvars
0%
0$
0#
0"
0!
$end
#100
1"
1!
1%
#200
0%
1$
#300
0!
1%
#400
0"
1!
0%
0$
1#
#500
0!
1%
#600
0%
1$
#700
1"
1!
1%
